HandySeg/__init__.py
HandySeg/line_segmentation.py
HandySeg/preprocessing.py
HandySeg/word_segmentaiton.py
HandySeg-0.7.0.dist-info/LICENSE
HandySeg-0.7.0.dist-info/METADATA
HandySeg-0.7.0.dist-info/WHEEL
HandySeg-0.7.0.dist-info/top_level.txt
HandySeg-0.7.0.dist-info/RECORD
