Metadata-Version: 2.1
Name: HandySeg
Version: 0.7.0
Summary: A package for line and word segmentation of handwritten scanned text
Home-page: https://github.com/saadraqib/HandySeg
Author: SaadRaqib
Author-email: saad.rqaziz@gmail.com
License: UNKNOWN
Platform: UNKNOWN
Classifier: Programming Language :: Python :: 3
Classifier: License :: OSI Approved :: MIT License
Classifier: Operating System :: OS Independent
Requires-Python: >=3.6
License-File: LICENSE
Requires-Dist: numpy
Requires-Dist: opencv-python
Requires-Dist: scipy
Requires-Dist: matplotlib
